setup.py
sandbox/__init__.py
sandbox/ec2-prices.py
sandbox/finder.py
sandbox/index_overflow_test.py
sandbox/migrate_specific.py
usergrid_util.egg-info/PKG-INFO
usergrid_util.egg-info/SOURCES.txt
usergrid_util.egg-info/dependency_links.txt
usergrid_util.egg-info/requires.txt
usergrid_util.egg-info/top_level.txt